LICENSE
MANIFEST.in
README.rst
setup.py
atxpdf/__init__.py
atxpdf/__main__.py
atxpdf/atxpdf.py
atxpdf/setup.py
atxpdf.egg-info/PKG-INFO
atxpdf.egg-info/SOURCES.txt
atxpdf.egg-info/dependency_links.txt
atxpdf.egg-info/entry_points.txt
atxpdf.egg-info/requires.txt
atxpdf.egg-info/top_level.txt