Metadata-Version: 1.0
Name: atxpdf
Version: 0.1.3
Summary: AtExpert PDF generator.
Home-page: http://example.org
Author: Frederik Van Leeckwyck
Author-email: hogeblekker@hotmail.com
License: UNKNOWN
Platform: UNKNOWN
